{
  "val_history": [
    {
      "epoch": 1,
      "loss": 0.04621781630663973,
      "timestamp": "2025-11-26T22:18:14.275692"
    },
    {
      "epoch": 2,
      "loss": 0.04619917294712321,
      "timestamp": "2025-11-26T22:18:14.332292"
    },
    {
      "epoch": 3,
      "loss": 0.04618340152523574,
      "timestamp": "2025-11-26T22:18:14.387486"
    },
    {
      "epoch": 4,
      "loss": 0.04616933197531166,
      "timestamp": "2025-11-26T22:18:14.444473"
    },
    {
      "epoch": 5,
      "loss": 0.04615646145775771,
      "timestamp": "2025-11-26T22:18:14.499394"
    },
    {
      "epoch": 6,
      "loss": 0.04614451165422168,
      "timestamp": "2025-11-26T22:18:14.556644"
    }
  ],
  "best_val_loss": 0.04621781630663973,
  "best_epoch": 1,
  "latest_val_loss": 0.04614451165422168,
  "last_epoch": 6,
  "updated_at": "2025-11-26T22:18:14.499394"
}